[
  {
    "course": "662589afbc0af416129f57dc",
    "imageURL": "https://example.com/certificate1.jpg",
    "Date": "2023-08-15T13:45:30.000Z"
  },
  {
    "course": "662c311907b70495ef57795c",
    "imageURL": "https://example.com/certificate2.jpg",
    "Date": "2022-11-23T04:12:10.000Z"
  },
  {
    "course": "662589afbc0af416129f57dc",
    "imageURL": "https://example.com/certificate3.jpg",
    "Date": "2022-10-05T21:30:45.000Z"
  },
  {
    "course": "662c311907b70495ef57795c",
    "imageURL": "https://example.com/certificate4.jpg",
    "Date": "2023-02-18T09:56:20.000Z"
  },
  {
    "course": "662589afbc0af416129f57dc",
    "imageURL": "https://example.com/certificate5.jpg",
    "Date": "2023-05-30T18:27:55.000Z"
  },
  {
    "course": "662c311907b70495ef57795d",
    "imageURL": "https://example.com/certificate6.jpg",
    "Date": "2023-07-10T08:38:40.000Z"
  },
  {
    "course": "662c311907b70495ef57795d",
    "imageURL": "https://example.com/certificate7.jpg",
    "Date": "2022-12-28T15:14:05.000Z"
  },
  {
    "course": "662589afbc0af416129f57dc",
    "imageURL": "https://example.com/certificate8.jpg",
    "Date": "2023-09-20T00:01:30.000Z"
  },
  {
    "course": "662589afbc0af416129f57dc",
    "imageURL": "https://example.com/certificate9.jpg",
    "Date": "2022-08-07T12:48:15.000Z"
  },
  {
    "course": "662589afbc0af416129f57dc",
    "imageURL": "https://example.com/certificate10.jpg",
    "Date": "2023-01-14T23:22:50.000Z"
  }
]
